ellipsisPySpark/__init__.py
ellipsisPySpark/parse.py
ellipsisPySpark-0.0.0.dist-info/LICENSE
ellipsisPySpark-0.0.0.dist-info/METADATA
ellipsisPySpark-0.0.0.dist-info/WHEEL
ellipsisPySpark-0.0.0.dist-info/top_level.txt
ellipsisPySpark-0.0.0.dist-info/RECORD
