Metadata-Version: 2.1
Name: ellipsisPySpark
Version: 0.0.0
Summary: Package to load Ellipsis raster and vector layers as pySpark DataFrames.
Home-page: https://github.com/ellipsis-drive/pySpark
Author: Daniel van der Maas
Author-email: daniel@ellipsis-drive.com
Classifier: Programming Language :: Python :: 3
Classifier: License :: OSI Approved :: MIT License
Classifier: Operating System :: OS Independent
Requires-Python: >=3.6
License-File: LICENSE
Requires-Dist: pandas
Requires-Dist: numpy
Requires-Dist: json
Requires-Dist: pyspark
Requires-Dist: ellipsis
Requires-Dist: math
